LICENSE.txt
README.md
pyproject.toml
src/toddler/__init__.py
src/toddler.egg-info/PKG-INFO
src/toddler.egg-info/SOURCES.txt
src/toddler.egg-info/dependency_links.txt
src/toddler.egg-info/requires.txt
src/toddler.egg-info/top_level.txt
src/toddler/chemistry/__init__.py
src/toddler/chemistry/cantera.py
src/toddler/chemistry/cantera2.py
src/toddler/chemistry/equilibrium.py
src/toddler/data/__init__.py
src/toddler/data/spectrum.py
src/toddler/data/filters/__init__.py
src/toddler/data/filters/robust.py
src/toddler/data/filters/sgolay.py
src/toddler/files/__init__.py
src/toddler/files/filenames.py
src/toddler/files/saving.py
src/toddler/physics/__init__.py
src/toddler/physics/const.py
src/toddler/physics/energy.py
src/toddler/physics/flow.py
src/toddler/physics/kinetics.py
src/toddler/physics/light.py
src/toddler/physics/radiation.py
src/toddler/physics/rgb.py
src/toddler/physics/thermodynamics.py
src/toddler/physics/transport.py