Metadata-Version: 2.1
Name: toddler
Version: 0.0.3
Summary: Tools and Operations for Data, Diagnostics, Light, and other Electromagnetic Radiation
Author-email: "M.D. Ruijzendaal" <martijn.ruijzendaal@gmail.com>
License: MIT License
Project-URL: Homepage, https://github.com/mruijzendaal/toddler
Project-URL: Bug Reports, https://github.com/mruijzendaal/toddler/issues
Project-URL: Source, https://github.com/mruijzendaal/toddler/
Keywords: toddler,optical diagnostics,numpy
Classifier: Development Status :: 3 - Alpha
Classifier: Intended Audience :: Developers
Classifier: Intended Audience :: Science/Research
Classifier: Topic :: Scientific/Engineering
Classifier: Topic :: Scientific/Engineering :: Image Processing
Classifier: Topic :: Scientific/Engineering :: Physics
Classifier: Topic :: Scientific/Engineering :: Mathematics
Classifier: License :: OSI Approved :: MIT License
Classifier: Programming Language :: Python :: 3
Classifier: Programming Language :: Python :: 3.8
Classifier: Programming Language :: Python :: 3.9
Classifier: Programming Language :: Python :: 3.10
Classifier: Programming Language :: Python :: 3.11
Classifier: Programming Language :: Python :: 3.12
Classifier: Programming Language :: Python :: 3 :: Only
Requires-Python: >=3.8
License-File: LICENSE.txt
Requires-Dist: numpy
Requires-Dist: sif_parser
Requires-Dist: pandas
Requires-Dist: scipy
